pypom_selenium/__init__.py
pypom_selenium/exception.py
pypom_selenium/page.py
pypom_selenium/py.typed
pypom_selenium/region.py
pypom_selenium/selenium_driver.py
pypom_selenium/view.py
pypom_selenium-2.0.1.dist-info/METADATA
pypom_selenium-2.0.1.dist-info/WHEEL
pypom_selenium-2.0.1.dist-info/licenses/LICENSE
pypom_selenium-2.0.1.dist-info/RECORD
