Metadata-Version: 2.4
Name: pypom-selenium
Version: 2.0.1
Summary: python page object model for selenium
Project-URL: Homepage, https://github.com/albinpalsson/pypom-selenium
Project-URL: Issues, https://github.com/albinpalsson/pypom-selenium/issues
Author: Albin Pålsson
License-File: LICENSE
Keywords: model,object,page,pypom,selenium
Classifier: License :: OSI Approved :: Mozilla Public License 2.0 (MPL 2.0)
Classifier: Operating System :: MacOS :: MacOS X
Classifier: Operating System :: Microsoft :: Windows
Classifier: Operating System :: POSIX
Classifier: Programming Language :: Python
Classifier: Programming Language :: Python :: 3.10
Classifier: Programming Language :: Python :: 3.12
Classifier: Programming Language :: Python :: 3.14
Requires-Python: >=3.8
Requires-Dist: selenium
Requires-Dist: typing-extensions
